qobuz_dl/__init__.py
qobuz_dl/bundle.py
qobuz_dl/cli.py
qobuz_dl/color.py
qobuz_dl/commands.py
qobuz_dl/core.py
qobuz_dl/db.py
qobuz_dl/downloader.py
qobuz_dl/exceptions.py
qobuz_dl/metadata.py
qobuz_dl/qopy.py
qobuz_dl/utils.py
qobuz_dlp-0.14.0.dist-info/LICENSE
qobuz_dlp-0.14.0.dist-info/METADATA
qobuz_dlp-0.14.0.dist-info/WHEEL
qobuz_dlp-0.14.0.dist-info/entry_points.txt
qobuz_dlp-0.14.0.dist-info/RECORD
