Metadata-Version: 2.1
Name: qobuz-dlp
Version: 0.14.0
Summary: A complete lossless and hi-res music downloader for Qobuz.
Home-page: https://github.com/infojunkie/qobuz-dlp.py
Author: infojunkie
Author-email: karim.ratib@gmail.com
Requires-Python: >=3.10,<4.0
Classifier: Programming Language :: Python :: 3
Classifier: Programming Language :: Python :: 3.10
Classifier: Programming Language :: Python :: 3.11
Requires-Dist: beautifulsoup4 (>=4.13.4,<5.0.0)
Requires-Dist: colorama (>=0.4.6,<0.5.0)
Requires-Dist: importlib-metadata (>=6.8.0,<7.0.0)
Requires-Dist: mutagen (>=1.46.0,<2.0.0)
Requires-Dist: pathvalidate (>=3.2.0,<4.0.0)
Requires-Dist: pick (==1.6.0)
Requires-Dist: requests (>=2.32.3,<3.0.0)
Requires-Dist: tqdm (>=4.67.1,<5.0.0)
Project-URL: Repository, https://github.com/infojunkie/qobuz-dlp.py
